didi/__init__.py
didi/cli.py
didi/color.py
didi/diff.py
didi/pager.py
didi/commands/__init__.py
didi/commands/shell_integration.py
didi/shell/git-didi.bash
didi/shell/git-didi.fish
git_didi-0.1.1.dist-info/licenses/LICENSE
git_didi-0.1.1.dist-info/METADATA
git_didi-0.1.1.dist-info/WHEEL
git_didi-0.1.1.dist-info/entry_points.txt
git_didi-0.1.1.dist-info/top_level.txt
git_didi-0.1.1.dist-info/RECORD
