Metadata-Version: 2.4
Name: git-didi
Version: 0.1.1
Summary: Compare diffs between two git ranges - a 'diff of diffs' tool for verifying rebases and tracking changes
Author-email: Ryan Williams <ryan@runsascoded.com>
License: MIT
Project-URL: Repository, https://github.com/runsascoded/git-didi
Project-URL: Issues, https://github.com/runsascoded/git-didi/issues
Keywords: git,diff,rebase,cli
Classifier: Development Status :: 3 - Alpha
Classifier: Intended Audience :: Developers
Classifier: License :: OSI Approved :: MIT License
Classifier: Programming Language :: Python :: 3
Classifier: Programming Language :: Python :: 3.10
Classifier: Programming Language :: Python :: 3.11
Classifier: Programming Language :: Python :: 3.12
Classifier: Programming Language :: Python :: 3.13
Requires-Python: >=3.10
License-File: LICENSE
Requires-Dist: click>=8.0
Requires-Dist: utz>=0.21.2
Provides-Extra: test
Requires-Dist: pytest>=7.0; extra == "test"
Dynamic: license-file
